{"name":"homebridge-tuya-ir","version":"0.0.12","dependencies":{"crypto-js":{"version":"4.0.0"},"request":{"version":"2.88.2","dependencies":{"aws-sign2":{"version":"0.7.0"},"aws4":{"version":"1.11.0"},"caseless":{"version":"0.12.0"},"combined-stream":{"version":"1.0.8","dependencies":{"delayed-stream":{"version":"1.0.0"}}},"extend":{"version":"3.0.2"},"forever-agent":{"version":"0.6.1"},"form-data":{"version":"2.3.3","dependencies":{"asynckit":{"version":"0.4.0"},"combined-stream":{"version":"1.0.8"},"mime-types":{"version":"2.1.31"}}},"har-validator":{"version":"5.1.5","dependencies":{"ajv":{"version":"6.12.6","dependencies":{"fast-deep-equal":{"version":"3.1.3"},"fast-json-stable-stringify":{"version":"2.1.0"},"json-schema-traverse":{"version":"0.4.1"},"uri-js":{"version":"4.4.1","dependencies":{"punycode":{"version":"2.1.1"}}}}},"har-schema":{"version":"2.0.0"}}},"http-signature":{"version":"1.2.0","dependencies":{"assert-plus":{"version":"1.0.0"},"jsprim":{"version":"1.4.1","dependencies":{"assert-plus":{"version":"1.0.0"},"extsprintf":{"version":"1.3.0"},"json-schema":{"version":"0.2.3"},"verror":{"version":"1.10.0","dependencies":{"assert-plus":{"version":"1.0.0"},"core-util-is":{"version":"1.0.2"},"extsprintf":{"version":"1.3.0"}}}}},"sshpk":{"version":"1.16.1","dependencies":{"asn1":{"version":"0.2.4","dependencies":{"safer-buffer":{"version":"2.1.2"}}},"assert-plus":{"version":"1.0.0"},"bcrypt-pbkdf":{"version":"1.0.2","dependencies":{"tweetnacl":{"version":"0.14.5"}}},"dashdash":{"version":"1.14.1","dependencies":{"assert-plus":{"version":"1.0.0"}}},"ecc-jsbn":{"version":"0.1.2","dependencies":{"jsbn":{"version":"0.1.1"},"safer-buffer":{"version":"2.1.2"}}},"getpass":{"version":"0.1.7","dependencies":{"assert-plus":{"version":"1.0.0"}}},"jsbn":{"version":"0.1.1"},"safer-buffer":{"version":"2.1.2"},"tweetnacl":{"version":"0.14.5"}}}}},"is-typedarray":{"version":"1.0.0"},"isstream":{"version":"0.1.2"},"json-stringify-safe":{"version":"5.0.1"},"mime-types":{"version":"2.1.31","dependencies":{"mime-db":{"version":"1.48.0"}}},"oauth-sign":{"version":"0.9.0"},"performance-now":{"version":"2.1.0"},"qs":{"version":"6.5.2"},"safe-buffer":{"version":"5.2.1"},"tough-cookie":{"version":"2.5.0","dependencies":{"psl":{"version":"1.8.0"},"punycode":{"version":"2.1.1"}}},"tunnel-agent":{"version":"0.6.0","dependencies":{"safe-buffer":{"version":"5.2.1"}}},"uuid":{"version":"3.4.0"}}}}}